imglp/__init__.py
imglp/modules/__init__.py
imglp/modules/crosscorrelate_LP/__init__.py
imglp/modules/crosscorrelate_LP/crosscorrelate.py
imglp/modules/crosscorrelate_LP/functions/__init__.py
imglp/modules/crosscorrelate_LP/functions/__template__.py
imglp/modules/crosscorrelate_LP/test_crosscorrelate.py
imglp/modules/drift_LP/__init__.py
imglp/modules/drift_LP/drift.py
imglp/modules/drift_LP/functions/__init__.py
imglp/modules/drift_LP/functions/__template__.py
imglp/modules/drift_LP/test_drift.py
imglp/py.typed
imglp/routines/__init__.py
imglp-0.1.12.dist-info/WHEEL
imglp-0.1.12.dist-info/METADATA
imglp-0.1.12.dist-info/RECORD
