Metadata-Version: 2.3
Name: imglp
Version: 0.1.12
Summary: A library that provides tools for image processing.
Requires-Dist: arrlp
Requires-Dist: corelp
Requires-Dist: imageio
Requires-Dist: imageio-ffmpeg
Requires-Dist: numba
Requires-Dist: numpy
Requires-Dist: pillow
Requires-Dist: scipy
Requires-Dist: tifffile
Requires-Python: >=3.12
